trueapi/__init__.py
trueapi-0.0.1.dist-info/LICENSE
trueapi-0.0.1.dist-info/METADATA
trueapi-0.0.1.dist-info/WHEEL
trueapi-0.0.1.dist-info/top_level.txt
trueapi-0.0.1.dist-info/RECORD
